thelethe/__init__.py
thelethe/olympians.py
thelethe/protogenois.py
thelethe/titans.py
thelethe/architectures/__init__.py
thelethe/architectures/olympians/__init__.py
thelethe/architectures/protogenois/__init__.py
thelethe/architectures/titans/__init__.py
thelethe/architectures/titans/configs.py
thelethe/architectures/titans/modelings.py
thelethe/architectures/titans/models/__init__.py
thelethe/architectures/titans/models/atlas/__init__.py
thelethe/architectures/titans/models/atlas/configuration_atlas.py
thelethe/architectures/titans/models/atlas/modeling_atlas.py
thelethe/architectures/titans/models/atlas/processing_atlas.py
thelethe/architectures/titans/models/origin/__init__.py
thelethe/architectures/titans/models/origin/configuration_origin.py
thelethe/architectures/titans/models/origin/modeling_origin.py
thelethe/architectures/titans/models/origin/processing_origin.py
thelethe/utils/logging.py
thelethe/utils/trainer.py
thelethe-0.0.1.dist-info/licenses/LICENSE
thelethe-0.0.1.dist-info/WHEEL
thelethe-0.0.1.dist-info/METADATA
thelethe-0.0.1.dist-info/RECORD
