Metadata-Version: 2.4
Name: thelethe
Version: 0.0.1
Summary: AI models with adaptive memory management and strategic forgetting, inspired by Greek mythology and neuroscience.
Author-email: RetentionLabs <retentionlabs.ai@gmail.com>
Requires-Python: >=3.9, <3.14
Classifier: Development Status :: 3 - Alpha
Classifier: Intended Audience :: Science/Research
Classifier: License :: OSI Approved :: MIT License
Classifier: Programming Language :: Python :: 3
Classifier: Programming Language :: Python :: 3.9
Classifier: Programming Language :: Python :: 3.10
Classifier: Programming Language :: Python :: 3.11
Classifier: Programming Language :: Python :: 3.12
Classifier: Programming Language :: Python :: 3.13
Classifier: Topic :: Scientific/Engineering :: Artificial Intelligence
License-File: LICENSE
Requires-Dist: numpy
Requires-Dist: torch>=2.0.0
Requires-Dist: transformers>=4.30.0
Requires-Dist: pytest>=7.0.0 ; extra == "dev"
Requires-Dist: black>=23.0.0 ; extra == "dev"
Requires-Dist: isort>=5.12.0 ; extra == "dev"
Requires-Dist: mypy>=1.0.0 ; extra == "dev"
Requires-Dist: sphinx>=6.0.0 ; extra == "docs"
Requires-Dist: sphinx-rtd-theme>=1.2.0 ; extra == "docs"
Project-URL: Bug Tracker, https://github.com/retentionlabs/theRiverLethe/issues
Project-URL: Documentation, https://retentionlabs.github.io/
Project-URL: Homepage, https://github.com/retentionlabs/theRiverLethe
Provides-Extra: dev
Provides-Extra: docs
